premium_bonds_prize_checker/__main__.py
premium_bonds_prize_checker-0.1.0.dist-info/METADATA
premium_bonds_prize_checker-0.1.0.dist-info/WHEEL
premium_bonds_prize_checker-0.1.0.dist-info/entry_points.txt
premium_bonds_prize_checker-0.1.0.dist-info/RECORD
